BigBuyPy/__init__.py
BigBuyPy/_catalog_api_methods.py
BigBuyPy/_module_api_methods.py
BigBuyPy/_order_api_methods.py
BigBuyPy/_shipping_api_methods.py
BigBuyPy/_tracking_api_methods.py
BigBuyPy/_user_api_methods.py
BigBuyPy/utils.py
tests/__init__.py
tests/test_catalog.py
BigBuyPy-0.0.2.dist-info/LICENSE
BigBuyPy-0.0.2.dist-info/METADATA
BigBuyPy-0.0.2.dist-info/WHEEL
BigBuyPy-0.0.2.dist-info/top_level.txt
BigBuyPy-0.0.2.dist-info/RECORD
