Metadata-Version: 2.1
Name: BigBuyPy
Version: 0.0.2
Summary: Big Buy connector for python
Home-page: https://github.com/devandrepascoa/BigBuyPy
Author: André Páscoa
Author-email: andre@pascoa.org
License: UNKNOWN
Platform: UNKNOWN
Classifier: Programming Language :: Python :: 3
Classifier: License :: OSI Approved :: MIT License
Classifier: Operating System :: OS Independent
Requires-Python: >=3.6
